{
  "language": "de",
  "url": "haufige-fragen",
  "title": "Häufig gestellte Fragen",
  "headline": "FAQ",
  "questions": [
    {
      "title": "Konzept",
      "answer": "Der EUROMAT präsentiert insgesamt 33 Behauptungen zu verschiedenen Politikfeldern der Europäischen Politik wie z. B. Migration oder Sicherheit, denen Du zustimmen, ablehnen oder neutral kommentieren kannst. Deine Antworten werden anschließend mit den Positionen der europäischen Parteien abgeglichen, und daraus wird ein Ranking auf Basis der prozentualen Übereinstimmung mit der jeweiligen Partei erstellt. Zusätzlich geben wir Dir einen Überblick über die Zuordnung der nationalen Parteien in den jeweiligen europäischen Parteien.\n\nFür die Zusammenstellung der Thesen und Antworten wurden insgesamt 21 europäische Parteien kontaktiert: European People's Party (EPP), Party of European Socialists (PES), Alliance of Conservatives and Reformists in Europe (ACRE), European Christian Political Movement (ECPM), Alliance of Liberals and Democrats for Europe (ALDE),  European Democratic Party (EDP), Party of the European Left (PEL), Nordic Green Left Alliance (NGLA), European Green Party (EGP),European Free Alliance (EFA), Movement for a Europe of Nations and Freedom (MENF), VOLT, Alliance for Peace and Freedom (APF), Alliance for European National Movements (AENM), Initiative of Communist and Workers' Parties, DiEM25, European Federalist Party,European Pirate Party (PPEU), Euro Animal 7 (EA7), Liberal South East European Network (LIBSEEN), Europe Democracy Esperanto (EDE).\n\nVon diesen 21 Parteien haben uns insgesamt 12 geantwortet. Da wir von 9 Parteien im Vorfeld leider keine Stellungnahme zu den einzelnen Behauptungen des EUROMAT erhalten haben, konnten wir sie daher nicht für die weitere Auswertung berücksichtigen."
    },
    {
      "title": "Methodik",
      "answer": "Das Berechnungsmodell des EUROMAT basiert auf dem Rechenmodell der Bundeszentrale für politische Bildung, welches lizenzfrei zur Verfügung steht: Creative Commons BY-NC-ND 3.0"
    }
  ]
}